mgrep.py
mgrep-0.1.6.dist-info/METADATA
mgrep-0.1.6.dist-info/WHEEL
mgrep-0.1.6.dist-info/entry_points.txt
mgrep-0.1.6.dist-info/top_level.txt
mgrep-0.1.6.dist-info/RECORD
