Metadata-Version: 2.1
Name: mgrep
Version: 0.1.6
Summary: UNKNOWN
Home-page: UNKNOWN
License: UNKNOWN
Platform: UNKNOWN
Requires-Python: >=3.4
Requires-Dist: Click
